aiosow/__init__.py
aiosow/autofill.py
aiosow/bindings.py
aiosow/command.py
aiosow/options.py
aiosow/perpetuate.py
aiosow/routines.py
aiosow/setup.py
aiosow-0.1.8.dist-info/METADATA
aiosow-0.1.8.dist-info/WHEEL
aiosow-0.1.8.dist-info/entry_points.txt
aiosow-0.1.8.dist-info/top_level.txt
aiosow-0.1.8.dist-info/RECORD
